<Script>
	<ScriptReference id="720" name="Create new IO Type"></ScriptReference>
	<ObjectList membercount="14">
		<Step hash="4B044ED90C0A7258817CAC6695D35448" id="89" name="# (comment)" enable="True">
			<Options>4</Options>
			<ParameterValues membercount="1">
				<Parameter type="Comment">
					<Comment value="Called from a button in IO Type List"></Comment>
				</Parameter>
			</ParameterValues>
		</Step>
		<Step hash="B62892B27C620694A209B43DD722F077" id="68" name="If" enable="True">
			<Options>16384</Options>
			<ParameterValues membercount="1">
				<Parameter type="Calculation">
					<Calculation datatype="7" position="0">
						<Calculation>
							<Text><![CDATA[FAT Title::gBaseProject = ""]]></Text>
						</Calculation>
					</Calculation>
				</Parameter>
			</ParameterValues>
		</Step>
		<Step hash="7B4EFEC83F610ABF66A7CBE7E084F0B4" id="87" name="Show Custom Dialog" enable="True">
			<Options>16389</Options>
			<ParameterValues membercount="5">
				<Parameter type="Title">
					<Calculation datatype="1" position="0">
						<Calculation>
							<Text><![CDATA["Select BaseProject"]]></Text>
						</Calculation>
					</Calculation>
				</Parameter>
				<Parameter type="Message">
					<Calculation datatype="1" position="1">
						<Calculation>
							<Text><![CDATA["You must select a BaseProject before creating a new IO type. "]]></Text>
						</Calculation>
					</Calculation>
				</Parameter>
				<Parameter type="Button1" value="OK">
					<Boolean type="Commit" value="True"></Boolean>
				</Parameter>
				<Parameter type="Button2">
					<Boolean type="Commit" value="False"></Boolean>
				</Parameter>
				<Parameter type="Button3">
					<Boolean type="Commit" value="False"></Boolean>
				</Parameter>
			</ParameterValues>
		</Step>
		<Step hash="0BD50561D742988BBC935CAE67D7B612" id="103" name="Exit Script" enable="True">
		</Step>
		<Step hash="D23AA5B0D1DA0803CCDDBF34BB681D17" id="70" name="End If" enable="True">
		</Step>
		<Step hash="D82FECD3493D97BF263268A9A41CCA60" id="141" name="Set Variable" enable="True">
			<Options>16388</Options>
			<ParameterValues membercount="1">
				<Parameter type="Variable">
					<value>
						<Calculation datatype="1" position="1">
							<Calculation>
								<Text><![CDATA[FAT Title::gBaseProject]]></Text>
							</Calculation>
						</Calculation>
					</value>
					<Name value="$baseproject_id"></Name>
					<repetition>
						<Calculation datatype="1" position="2">
							<Calculation>
								<Text><![CDATA[1]]></Text>
							</Calculation>
						</Calculation>
					</repetition>
				</Parameter>
			</ParameterValues>
		</Step>
		<Step hash="BD473BBB9799C19A56A5A9BF8D4AFB6A" id="87" name="Show Custom Dialog" enable="True">
			<Options>16389</Options>
			<ParameterValues membercount="7">
				<Parameter type="Title">
					<Calculation datatype="1" position="0">
						<Calculation>
							<Text><![CDATA["Creating a new IO Type"]]></Text>
						</Calculation>
					</Calculation>
				</Parameter>
				<Parameter type="Message">
					<Calculation datatype="1" position="1">
						<Calculation>
							<Text><![CDATA["You must enter IO Type for both FAT and Funkis Cloud backend. Both are case-sensitive. "]]></Text>
						</Calculation>
					</Calculation>
				</Parameter>
				<Parameter type="Button1" value="OK">
					<Boolean type="Commit" value="True"></Boolean>
				</Parameter>
				<Parameter type="Button2">
					<Boolean type="Commit" value="False"></Boolean>
				</Parameter>
				<Parameter type="Button3">
					<Boolean type="Commit" value="False"></Boolean>
				</Parameter>
				<Parameter type="Field1">
					<Parameter type="Target">
						<Variable value="$cmt_type">
							<repetition>
								<Calculation datatype="1" position="10">
									<Calculation>
										<Text><![CDATA[1]]></Text>
									</Calculation>
								</Calculation>
							</repetition>
						</Variable>
					</Parameter>
					<Boolean type="Password" value="False"></Boolean>
					<Parameter type="Label">
						<Calculation datatype="1" position="2">
							<Calculation>
								<Text><![CDATA["CMT IO type"]]></Text>
							</Calculation>
						</Calculation>
					</Parameter>
				</Parameter>
				<Parameter type="Field2">
					<Parameter type="Target">
						<Variable value="$quid_type">
							<repetition>
								<Calculation datatype="1" position="10">
									<Calculation>
										<Text><![CDATA[1]]></Text>
									</Calculation>
								</Calculation>
							</repetition>
						</Variable>
					</Parameter>
					<Boolean type="Password" value="False"></Boolean>
					<Parameter type="Label">
						<Calculation datatype="1" position="3">
							<Calculation>
								<Text><![CDATA["Quid type"]]></Text>
							</Calculation>
						</Calculation>
					</Parameter>
				</Parameter>
			</ParameterValues>
		</Step>
		<Step hash="A6DB28BF712E37194655E58B6C32C8BE" id="68" name="If" enable="True">
			<Options>16384</Options>
			<ParameterValues membercount="1">
				<Parameter type="Calculation">
					<Calculation datatype="7" position="0">
						<Calculation>
							<Text><![CDATA[Get(lastMessageChoice) = 1]]></Text>
						</Calculation>
					</Calculation>
				</Parameter>
			</ParameterValues>
		</Step>
		<Step hash="9851E73F8301A6A7DBE4D666D19DAF31" id="7" name="New Record/Request" enable="True">
		</Step>
		<Step hash="FE9BD1C05999B600655F90E771767672" id="76" name="Set Field" enable="True">
			<Options>16385</Options>
			<ParameterValues membercount="2">
				<Parameter type="FieldReference">
					<FieldReference id="12" name="Base Project">
						<repetition>
							<Calculation datatype="1" position="10">
								<Calculation>
									<Text><![CDATA[1]]></Text>
								</Calculation>
							</Calculation>
						</repetition>
						<TableOccurrenceReference id="1065524" name="IO Type"></TableOccurrenceReference>
					</FieldReference>
				</Parameter>
				<Parameter type="Calculation">
					<Calculation datatype="1" position="0">
						<Calculation>
							<Text><![CDATA[$baseproject_id]]></Text>
						</Calculation>
					</Calculation>
				</Parameter>
			</ParameterValues>
		</Step>
		<Step hash="048F14D5F0C17C971F0398B29779AEA3" id="76" name="Set Field" enable="True">
			<Options>16385</Options>
			<ParameterValues membercount="2">
				<Parameter type="FieldReference">
					<FieldReference id="7" name="FATType">
						<repetition>
							<Calculation datatype="1" position="10">
								<Calculation>
									<Text><![CDATA[1]]></Text>
								</Calculation>
							</Calculation>
						</repetition>
						<TableOccurrenceReference id="1065524" name="IO Type"></TableOccurrenceReference>
					</FieldReference>
				</Parameter>
				<Parameter type="Calculation">
					<Calculation datatype="1" position="0">
						<Calculation>
							<Text><![CDATA[$cmt_type]]></Text>
						</Calculation>
					</Calculation>
				</Parameter>
			</ParameterValues>
		</Step>
		<Step hash="C293FA1F169B38E8BE279D8170DF7981" id="76" name="Set Field" enable="True">
			<Options>16385</Options>
			<ParameterValues membercount="2">
				<Parameter type="FieldReference">
					<FieldReference id="6" name="QuidType">
						<repetition>
							<Calculation datatype="1" position="10">
								<Calculation>
									<Text><![CDATA[1]]></Text>
								</Calculation>
							</Calculation>
						</repetition>
						<TableOccurrenceReference id="1065524" name="IO Type"></TableOccurrenceReference>
					</FieldReference>
				</Parameter>
				<Parameter type="Calculation">
					<Calculation datatype="1" position="0">
						<Calculation>
							<Text><![CDATA[$quid_type]]></Text>
						</Calculation>
					</Calculation>
				</Parameter>
			</ParameterValues>
		</Step>
		<Step hash="2E75C43079057DDAF7FA276F30856F2B" id="89" name="# (comment)" enable="True">
			<ParameterValues membercount="1">
				<Parameter type="Comment">
					<Comment></Comment>
				</Parameter>
			</ParameterValues>
		</Step>
		<Step hash="7A15C3B75A663009CF912D9039C8B8F8" id="70" name="End If" enable="True">
		</Step>
	</ObjectList>
</Script>
