<TableOccurrence View="Related" height="60" id="1065626" name="Codebase PK Version VL" type="Local">
	<UUID modifications="48" userName="jensthorsen" accountName="jensthorsen" timestamp="2025-05-09T19:48:40">1E118633-F832-4994-879B-D517B0C9D27A</UUID>
	<BaseTableSourceReference type="BaseTableReference">
		<BaseTableReference id="227" name="Baseproject Codebase Version"></BaseTableReference>
	</BaseTableSourceReference>
	<CoordRect top="1575" left="3436" bottom="1693" right="3591"></CoordRect>
	<Color red="120" green="120" blue="120" alpha="1.00"></Color>
</TableOccurrence>
