<TableOccurrence View="Collapse" height="132" id="1065945" name="FAT List item @ IO Condition @ List VL" type="Local">
	<UUID modifications="24" userName="jensthorsen" accountName="jensthorsen" timestamp="2025-09-29T19:01:41">BFB85B7B-CC4D-49B5-B5C6-D2EF8899AE98</UUID>
	<BaseTableSourceReference type="BaseTableReference">
		<BaseTableReference id="180" name="FAT List item"></BaseTableReference>
	</BaseTableSourceReference>
	<CoordRect top="618" left="2926" bottom="796" right="3164"></CoordRect>
	<Color red="43" green="71" blue="20" alpha="1.00"></Color>
</TableOccurrence>
