<TableOccurrence View="Collapse" height="60" id="1065442" name="TF PI Text 7 TRANS 2" type="Local">
	<UUID modifications="19" userName="jensthorsen" accountName="jensthorsen" timestamp="2025-05-09T19:48:30">B9B87D53-3737-4A2F-8FFC-4AF0C45DDE36</UUID>
	<BaseTableSourceReference type="BaseTableReference">
		<BaseTableReference id="164" name="FAT Text"></BaseTableReference>
	</BaseTableSourceReference>
	<CoordRect top="2516" left="5509" bottom="2634" right="5639"></CoordRect>
	<Color red="217" green="11" blue="0" alpha="1.00"></Color>
</TableOccurrence>
