<Layout id="326" name="TABLE FAT Package Alt" width="1024">
	<TableOccurrenceReference id="1065506" name="FAT Package Alt"></TableOccurrenceReference>
	<LayoutThemeReference id="5" name="com.filemaker.theme.custom.6D5ECB31_A76C_471D_A58C_57A942AAD7D1" Display="Funkis FAT" Base="com.filemaker.theme.universal_touch"></LayoutThemeReference>
	<PartsList membercount="2">
		<Part type="Body" kind="4">
			<Definition type="Body" kind="4" size="1115" absolute="0" Options="0"></Definition>
			<ObjectList membercount="5">
				<LayoutObject hash="688638224C0FD12E414A86116AF86748" id="43" type="Edit Box" name="" kind="1">
					<Bounds top="76" left="108" bottom="121" right="187"></Bounds>
					<Options>805306368</Options>
					<Field>
						<FieldReference id="11" name="PrimaryKey" repetition="1">
							<TableOccurrenceReference id="1065506" name="FAT Package Alt"></TableOccurrenceReference>
						</FieldReference>
						<Options>1048592</Options>
						<Display Style="0" show="1"></Display>
						<Usage inputMode="0" type="1"></Usage>
					</Field>
					<ExtendedAttributes>
						<Formatting>
							<Graphic>
								<Options>5</Options>
							</Graphic>
							<Time>
								<Options>159</Options>
							</Time>
							<Numeric>
								<Options>256</Options>
								<Style>
									<Negative>
										<Color red="221" green="0" blue="0" alpha="1.00"></Color>
									</Negative>
								</Style>
								<DecimalDigits>2</DecimalDigits>
							</Numeric>
						</Formatting>
					</ExtendedAttributes>
				</LayoutObject>
				<LayoutObject hash="3BA8F2782CA11F9DFA57ADEB78D67030" id="44" type="Edit Box" name="" kind="1">
					<Bounds top="76" left="211" bottom="121" right="457"></Bounds>
					<Options>805306368</Options>
					<Field>
						<FieldReference id="54" name="Reference name" repetition="1">
							<TableOccurrenceReference id="1065506" name="FAT Package Alt"></TableOccurrenceReference>
						</FieldReference>
						<Options>1048592</Options>
						<Display Style="0" show="1"></Display>
						<Usage inputMode="0" type="1"></Usage>
					</Field>
					<ExtendedAttributes>
						<Formatting>
							<Graphic>
								<Options>5</Options>
							</Graphic>
							<Time>
								<Options>159</Options>
							</Time>
							<Numeric>
								<Options>256</Options>
								<Style>
									<Negative>
										<Color red="221" green="0" blue="0" alpha="1.00"></Color>
									</Negative>
								</Style>
								<DecimalDigits>2</DecimalDigits>
							</Numeric>
						</Formatting>
					</ExtendedAttributes>
				</LayoutObject>
				<LayoutObject hash="B22F6C4CD74C47B99764E58BF658A18B" id="45" type="Edit Box" name="" kind="1">
					<Bounds top="76" left="466" bottom="121" right="712"></Bounds>
					<Options>805306376</Options>
					<Field>
						<FieldReference id="85" name="Package type name" repetition="1">
							<TableOccurrenceReference id="1065506" name="FAT Package Alt"></TableOccurrenceReference>
						</FieldReference>
						<Options>1048592</Options>
						<Display Style="0" show="1"></Display>
						<Usage inputMode="0" type="1"></Usage>
					</Field>
					<ExtendedAttributes>
						<Formatting>
							<Graphic>
								<Options>5</Options>
							</Graphic>
							<Time>
								<Options>159</Options>
							</Time>
							<Numeric>
								<Options>256</Options>
								<Style>
									<Negative>
										<Color red="221" green="0" blue="0" alpha="1.00"></Color>
									</Negative>
								</Style>
								<DecimalDigits>2</DecimalDigits>
							</Numeric>
						</Formatting>
					</ExtendedAttributes>
				</LayoutObject>
				<LayoutObject hash="87D421C923C03C1AA1689003180F35A8" id="46" type="Edit Box" name="" kind="1">
					<Bounds top="144" left="475" bottom="189" right="721"></Bounds>
					<Options>805306376</Options>
					<Field>
						<FieldReference id="83" name="Usage type id" repetition="1">
							<TableOccurrenceReference id="1065506" name="FAT Package Alt"></TableOccurrenceReference>
						</FieldReference>
						<Display Style="0" show="1"></Display>
						<Usage inputMode="0" type="1"></Usage>
					</Field>
					<ExtendedAttributes>
						<Formatting>
							<Graphic>
								<Options>5</Options>
							</Graphic>
							<Time>
								<Options>159</Options>
							</Time>
							<Numeric>
								<Options>256</Options>
								<Style>
									<Negative>
										<Color red="221" green="0" blue="0" alpha="1.00"></Color>
									</Negative>
								</Style>
								<DecimalDigits>2</DecimalDigits>
							</Numeric>
						</Formatting>
					</ExtendedAttributes>
				</LayoutObject>
				<LayoutObject hash="3087EEFB6549F2E480BB7F46B787D8A6" id="47" type="Edit Box" name="" kind="1">
					<Bounds top="212" left="466" bottom="257" right="712"></Bounds>
					<Options>805306376</Options>
					<Field>
						<FieldReference id="97" name="Usage type name" repetition="1">
							<TableOccurrenceReference id="1065506" name="FAT Package Alt"></TableOccurrenceReference>
						</FieldReference>
						<Display Style="0" show="1"></Display>
						<Usage inputMode="0" type="1"></Usage>
					</Field>
					<ExtendedAttributes>
						<Formatting>
							<Graphic>
								<Options>5</Options>
							</Graphic>
							<Time>
								<Options>159</Options>
							</Time>
							<Numeric>
								<Options>256</Options>
								<Style>
									<Negative>
										<Color red="221" green="0" blue="0" alpha="1.00"></Color>
									</Negative>
								</Style>
								<DecimalDigits>2</DecimalDigits>
							</Numeric>
						</Formatting>
					</ExtendedAttributes>
				</LayoutObject>
			</ObjectList>
		</Part>
		<Part type="Footer" kind="7">
			<Definition type="Footer" kind="7" size="34" absolute="1115" Options="0"></Definition>
		</Part>
	</PartsList>
	<UUID modifications="77" userName="jensthorsen" accountName="jensthorsen" timestamp="2025-10-22T10:45:14">2215E26E-B898-4FFC-AEDF-21C854337843</UUID>
	<ClientType>0</ClientType>
	<Options hidden="False">351488519</Options>
	<MenuSet>
		<CustomMenuSetReference id="0" name="[File Default]"></CustomMenuSetReference>
	</MenuSet>
</Layout>
