<Relationship id="225">
	<UUID modifications="2" userName="Erik Wiberg" accountName="erik.wiberg@funkismultimedia.se" timestamp="2022-10-27T16:01:05">98B54DB0-5DE4-4794-A1F3-D3D74D3C6D96</UUID>
	<LeftTable cascadeCreate="False" cascadeDelete="True" type="Local">
		<TableOccurrenceReference id="1065301" name="TF PI Text 7 TRANS"></TableOccurrenceReference>
		<SortSpecification value="False" maintain="True"></SortSpecification>
	</LeftTable>
	<RightTable cascadeCreate="False" cascadeDelete="False" type="Local">
		<TableOccurrenceReference id="1065129" name="FAT Page item"></TableOccurrenceReference>
		<SortSpecification value="False" maintain="True"></SortSpecification>
	</RightTable>
	<JoinPredicateList membercount="2">
		<JoinPredicate type="Equal">
			<LeftField>
				<FieldReference id="13" name="OriginalKey">
					<TableOccurrenceReference id="1065301" name="TF PI Text 7 TRANS"></TableOccurrenceReference>
				</FieldReference>
			</LeftField>
			<RightField>
				<FieldReference id="59" name="Text 7 id">
					<TableOccurrenceReference id="1065129" name="FAT Page item"></TableOccurrenceReference>
				</FieldReference>
			</RightField>
		</JoinPredicate>
		<JoinPredicate type="Equal">
			<LeftField>
				<FieldReference id="22" name="Localisation code">
					<TableOccurrenceReference id="1065301" name="TF PI Text 7 TRANS"></TableOccurrenceReference>
				</FieldReference>
			</LeftField>
			<RightField>
				<FieldReference id="31" name="Current localisation code">
					<TableOccurrenceReference id="1065129" name="FAT Page item"></TableOccurrenceReference>
				</FieldReference>
			</RightField>
		</JoinPredicate>
	</JoinPredicateList>
</Relationship>
