<Relationship id="633">
	<UUID modifications="2" userName="jensthorsen" accountName="jensthorsen" timestamp="2023-05-18T09:50:32">9553B730-BF6F-4191-928A-7F509A158E58</UUID>
	<LeftTable cascadeCreate="False" cascadeDelete="True" type="Local">
		<TableOccurrenceReference id="1065697" name="TF SR Name"></TableOccurrenceReference>
		<SortSpecification value="False" maintain="True"></SortSpecification>
	</LeftTable>
	<RightTable cascadeCreate="False" cascadeDelete="False" type="Local">
		<TableOccurrenceReference id="1065686" name="FAT Score Reward"></TableOccurrenceReference>
		<SortSpecification value="False" maintain="True"></SortSpecification>
	</RightTable>
	<JoinPredicateList membercount="1">
		<JoinPredicate type="Equal">
			<LeftField>
				<FieldReference id="1" name="PrimaryKey">
					<TableOccurrenceReference id="1065697" name="TF SR Name"></TableOccurrenceReference>
				</FieldReference>
			</LeftField>
			<RightField>
				<FieldReference id="11" name="Name text id">
					<TableOccurrenceReference id="1065686" name="FAT Score Reward"></TableOccurrenceReference>
				</FieldReference>
			</RightField>
		</JoinPredicate>
	</JoinPredicateList>
</Relationship>
