<FieldCatalog>
	<UUID modifications="78" userName="jensthorsen" accountName="jensthorsen" timestamp="2025-04-15T18:34:41">4B44A449-A1DE-426C-BF5B-C6535CF03E1C</UUID>
	<BaseTableReference id="167" name="Variables"></BaseTableReference>
	<ObjectList membercount="47">
		<Field id="6" name="Google API key" fieldtype="Normal" datatype="Text" comment="">
			<UUID modifications="2" userName="Erik Wiberg" accountName="erik.wiberg@funkismultimedia.se" timestamp="2022-10-27T16:01:02">DA17A583-1B32-402A-B729-43B685F8F144</UUID>
			<AutoEnter type="" prohibitModification="False"></AutoEnter>
			<Validation type="OnlyDuringDataEntry" allowOverride="True" notEmpty="False" unique="False" existing="False"></Validation>
			<Storage global="True" maxRepetitions="1">
				<LanguageReference name="Swedish" id="41"></LanguageReference>
			</Storage>
		</Field>
		<Field id="10" name="gSMTP server" fieldtype="Normal" datatype="Text" comment="">
			<UUID modifications="2" userName="Erik Wiberg" accountName="erik.wiberg@funkismultimedia.se" timestamp="2022-10-27T16:01:02">9DDFFF56-EF81-4DFE-8563-FE820D0D937C</UUID>
			<AutoEnter type="" prohibitModification="False"></AutoEnter>
			<Validation type="OnlyDuringDataEntry" allowOverride="True" notEmpty="False" unique="False" existing="False"></Validation>
			<Storage global="True" maxRepetitions="1">
				<LanguageReference name="English" id="21"></LanguageReference>
			</Storage>
		</Field>
		<Field id="11" name="gSMTP username" fieldtype="Normal" datatype="Text" comment="">
			<UUID modifications="2" userName="Erik Wiberg" accountName="erik.wiberg@funkismultimedia.se" timestamp="2022-10-27T16:01:02">814759E2-972C-484F-9DFE-A4ECEB86557E</UUID>
			<AutoEnter type="" prohibitModification="False"></AutoEnter>
			<Validation type="OnlyDuringDataEntry" allowOverride="True" notEmpty="False" unique="False" existing="False"></Validation>
			<Storage global="True" maxRepetitions="1">
				<LanguageReference name="English" id="21"></LanguageReference>
			</Storage>
		</Field>
		<Field id="12" name="gSMTP password" fieldtype="Normal" datatype="Text" comment="">
			<UUID modifications="2" userName="Erik Wiberg" accountName="erik.wiberg@funkismultimedia.se" timestamp="2022-10-27T16:01:02">18F0700F-D6D3-49CE-85FE-723C250F7F58</UUID>
			<AutoEnter type="" prohibitModification="False"></AutoEnter>
			<Validation type="OnlyDuringDataEntry" allowOverride="True" notEmpty="False" unique="False" existing="False"></Validation>
			<Storage global="True" maxRepetitions="1">
				<LanguageReference name="English" id="21"></LanguageReference>
			</Storage>
		</Field>
		<Field id="13" name="gLayoutname login" fieldtype="Normal" datatype="Text" comment="">
			<UUID modifications="2" userName="Erik Wiberg" accountName="erik.wiberg@funkismultimedia.se" timestamp="2022-10-27T16:01:02">4697AAC9-748E-440D-ABC7-5D2D591C6F12</UUID>
			<AutoEnter type="" prohibitModification="False"></AutoEnter>
			<Validation type="OnlyDuringDataEntry" allowOverride="True" notEmpty="False" unique="False" existing="False"></Validation>
			<Storage global="True" maxRepetitions="1">
				<LanguageReference name="English" id="21"></LanguageReference>
			</Storage>
		</Field>
		<Field id="16" name="gLanguage" fieldtype="Normal" datatype="Text" comment="">
			<UUID modifications="2" userName="Erik Wiberg" accountName="erik.wiberg@funkismultimedia.se" timestamp="2022-10-27T16:01:02">72A737CB-0D3A-4E7A-B81D-99730EFDB032</UUID>
			<AutoEnter type="" prohibitModification="False"></AutoEnter>
			<Validation type="OnlyDuringDataEntry" allowOverride="True" notEmpty="False" unique="False" existing="False"></Validation>
			<Storage global="True" maxRepetitions="1">
				<LanguageReference name="English" id="21"></LanguageReference>
			</Storage>
		</Field>
		<Field id="19" name="gFTP username" fieldtype="Normal" datatype="Text" comment="">
			<UUID modifications="3" userName="Erik Wiberg" accountName="erik.wiberg@funkismultimedia.se" timestamp="2022-10-27T16:01:02">AA0246E0-55BC-40DD-B872-C6E6EEE9CFF4</UUID>
			<AutoEnter type="" prohibitModification="False"></AutoEnter>
			<Validation type="OnlyDuringDataEntry" allowOverride="True" notEmpty="False" unique="False" existing="False"></Validation>
			<Storage global="True" maxRepetitions="1">
				<LanguageReference name="English" id="21"></LanguageReference>
			</Storage>
		</Field>
		<Field id="20" name="gFTP password" fieldtype="Normal" datatype="Text" comment="">
			<UUID modifications="3" userName="Erik Wiberg" accountName="erik.wiberg@funkismultimedia.se" timestamp="2022-10-27T16:01:02">050F0020-1F34-4BD8-BF18-60D1A3DDFC42</UUID>
			<AutoEnter type="" prohibitModification="False"></AutoEnter>
			<Validation type="OnlyDuringDataEntry" allowOverride="True" notEmpty="False" unique="False" existing="False"></Validation>
			<Storage global="True" maxRepetitions="1">
				<LanguageReference name="English" id="21"></LanguageReference>
			</Storage>
		</Field>
		<Field id="21" name="gFTP server" fieldtype="Normal" datatype="Text" comment="">
			<UUID modifications="3" userName="Erik Wiberg" accountName="erik.wiberg@funkismultimedia.se" timestamp="2022-10-27T16:01:02">CD4F974B-015D-40CD-BFB7-2F215C3130D0</UUID>
			<AutoEnter type="" prohibitModification="False"></AutoEnter>
			<Validation type="OnlyDuringDataEntry" allowOverride="True" notEmpty="False" unique="False" existing="False"></Validation>
			<Storage global="True" maxRepetitions="1">
				<LanguageReference name="English" id="21"></LanguageReference>
			</Storage>
		</Field>
		<Field id="22" name="gContainer" fieldtype="Normal" datatype="Binary" comment="">
			<UUID modifications="2" userName="Erik Wiberg" accountName="erik.wiberg@funkismultimedia.se" timestamp="2022-10-27T16:01:02">FEC85120-950E-4AFF-8292-EE7EC731536E</UUID>
			<AutoEnter type="" prohibitModification="False"></AutoEnter>
			<Validation type="OnlyDuringDataEntry" allowOverride="True" notEmpty="False" unique="False" existing="False"></Validation>
			<Storage global="True" maxRepetitions="1"></Storage>
		</Field>
		<Field id="23" name="gHTTP server" fieldtype="Normal" datatype="Text" comment="">
			<UUID modifications="3" userName="Erik Wiberg" accountName="erik.wiberg@funkismultimedia.se" timestamp="2022-10-27T16:01:02">0D80995E-A08A-4248-BA6C-90F2F31ED16B</UUID>
			<AutoEnter type="" prohibitModification="False"></AutoEnter>
			<Validation type="OnlyDuringDataEntry" allowOverride="True" notEmpty="False" unique="False" existing="False"></Validation>
			<Storage global="True" maxRepetitions="1">
				<LanguageReference name="Swedish" id="41"></LanguageReference>
			</Storage>
		</Field>
		<Field id="25" name="Google Cloud funkis cms API key" fieldtype="Normal" datatype="Text" comment="Use with AutoML translation">
			<UUID modifications="3" userName="Erik Wiberg" accountName="erik.wiberg@funkismultimedia.se" timestamp="2022-10-27T16:01:02">6F3AD853-EB9F-4A47-87D3-AF5987B40E7B</UUID>
			<AutoEnter type="" prohibitModification="False"></AutoEnter>
			<Validation type="OnlyDuringDataEntry" allowOverride="True" notEmpty="False" unique="False" existing="False"></Validation>
			<Storage global="True" maxRepetitions="1">
				<LanguageReference name="Swedish" id="41"></LanguageReference>
			</Storage>
		</Field>
		<Field id="26" name="GoogleService account JSON" fieldtype="Normal" datatype="Binary" comment="">
			<UUID modifications="1" userName="Erik Wiberg" accountName="erik.wiberg@funkismultimedia.se" timestamp="2022-10-27T16:01:02">E9B465C1-C984-4FD8-A430-77F57FF4ADAE</UUID>
			<AutoEnter type="" prohibitModification="False"></AutoEnter>
			<Validation type="OnlyDuringDataEntry" allowOverride="True" notEmpty="False" unique="False" existing="False"></Validation>
			<Storage global="False" maxRepetitions="1"></Storage>
		</Field>
		<Field id="27" name="Google Web account JSON" fieldtype="Normal" datatype="Binary" comment="">
			<UUID modifications="1" userName="Erik Wiberg" accountName="erik.wiberg@funkismultimedia.se" timestamp="2022-10-27T16:01:02">53D5F41D-12D7-49C0-8B54-14A966D19438</UUID>
			<AutoEnter type="" prohibitModification="False"></AutoEnter>
			<Validation type="OnlyDuringDataEntry" allowOverride="True" notEmpty="False" unique="False" existing="False"></Validation>
			<Storage global="False" maxRepetitions="1"></Storage>
		</Field>
		<Field id="28" name="Title default image Funkis Cloud" fieldtype="Normal" datatype="Binary" comment="">
			<UUID modifications="2" userName="jensthorsen" accountName="jensthorsen" timestamp="2023-08-13T10:40:12">DC8E5690-E607-4E69-9C1F-6B20A7CF6E11</UUID>
			<AutoEnter type="" prohibitModification="False"></AutoEnter>
			<Validation type="OnlyDuringDataEntry" allowOverride="True" notEmpty="False" unique="False" existing="False"></Validation>
			<Storage global="False" maxRepetitions="1"></Storage>
		</Field>
		<Field id="29" name="Webviewer HTML TextField Alt" fieldtype="Normal" datatype="Text" comment="">
			<UUID modifications="3" userName="jensthorsen" accountName="jensthorsen" timestamp="2025-04-15T18:34:40">BF4DCD7C-B703-4862-8B7C-1E237D3AC145</UUID>
			<AutoEnter type="" prohibitModification="False"></AutoEnter>
			<Validation type="OnlyDuringDataEntry" allowOverride="True" notEmpty="False" unique="False" existing="False"></Validation>
			<Storage autoIndex="True" global="False" maxRepetitions="1">
				<LanguageReference name="Swedish" id="41"></LanguageReference>
			</Storage>
		</Field>
		<Field id="30" name="gFAT URL" fieldtype="Normal" datatype="Text" comment="">
			<UUID modifications="3" userName="jensthorsen" accountName="jensthorsen" timestamp="2022-05-09T21:10:02">B4F8F3FC-61D7-41CE-A877-6C5619801A71</UUID>
			<AutoEnter type="" prohibitModification="False"></AutoEnter>
			<Validation type="OnlyDuringDataEntry" allowOverride="True" notEmpty="False" unique="False" existing="False"></Validation>
			<Storage global="True" maxRepetitions="1">
				<LanguageReference name="Swedish" id="41"></LanguageReference>
			</Storage>
		</Field>
		<Field id="33" name="gTranslateThroughGoogleML server" fieldtype="Normal" datatype="Text" comment="">
			<UUID modifications="3" userName="Erik Wiberg" accountName="erik.wiberg@funkismultimedia.se" timestamp="2022-10-27T16:01:02">175C441A-34F6-4E73-96C4-EB7B082AD81E</UUID>
			<AutoEnter type="" prohibitModification="False"></AutoEnter>
			<Validation type="OnlyDuringDataEntry" allowOverride="True" notEmpty="False" unique="False" existing="False"></Validation>
			<Storage global="True" maxRepetitions="1">
				<LanguageReference name="Swedish" id="41"></LanguageReference>
			</Storage>
		</Field>
		<Field id="34" name="taskServerURL" fieldtype="Normal" datatype="Text" comment="">
			<UUID modifications="5" userName="Jens Thorsen" accountName="jensthorsen" timestamp="2022-01-21T10:47:47">66DA4986-A9B9-4C4C-A58C-4254153E3787</UUID>
			<AutoEnter type="" prohibitModification="False"></AutoEnter>
			<Validation type="OnlyDuringDataEntry" allowOverride="True" notEmpty="False" unique="False" existing="False"></Validation>
			<Storage global="True" maxRepetitions="1">
				<LanguageReference name="English" id="21"></LanguageReference>
			</Storage>
		</Field>
		<Field id="35" name="gCMT WebViewer HTML URL" fieldtype="Normal" datatype="Text" comment="">
			<UUID modifications="4" userName="Erik Wiberg" accountName="erik.wiberg@funkismultimedia.se" timestamp="2022-10-27T16:01:02">E86525AD-A5F3-4EF6-80CA-A8EAD7BB939D</UUID>
			<AutoEnter type="" prohibitModification="False"></AutoEnter>
			<Validation type="OnlyDuringDataEntry" allowOverride="True" notEmpty="False" unique="False" existing="False"></Validation>
			<Storage global="True" maxRepetitions="1">
				<LanguageReference name="Swedish" id="41"></LanguageReference>
			</Storage>
		</Field>
		<Field id="36" name="Google Cloud Translation API URL" fieldtype="Normal" datatype="Text" comment="">
			<UUID modifications="3" userName="Erik Wiberg" accountName="erik.wiberg@funkismultimedia.se" timestamp="2022-10-27T16:01:02">00908F82-2D7C-4CEE-86BA-B77BE6720EB6</UUID>
			<AutoEnter type="" prohibitModification="False"></AutoEnter>
			<Validation type="OnlyDuringDataEntry" allowOverride="True" notEmpty="False" unique="False" existing="False"></Validation>
			<Storage global="True" maxRepetitions="1">
				<LanguageReference name="Swedish" id="41"></LanguageReference>
			</Storage>
		</Field>
		<Field id="37" name="WebViewer HTML PageItem" fieldtype="Normal" datatype="Text" comment="">
			<UUID modifications="1" userName="jensthorsen" accountName="jensthorsen" timestamp="2020-07-15T11:37:33">25ECE120-2252-485B-8511-A80E37E0E50D</UUID>
			<AutoEnter type="" prohibitModification="False"></AutoEnter>
			<Validation type="OnlyDuringDataEntry" allowOverride="True" notEmpty="False" unique="False" existing="False"></Validation>
			<Storage autoIndex="True" global="False" maxRepetitions="1">
				<LanguageReference name="Swedish" id="41"></LanguageReference>
			</Storage>
		</Field>
		<Field id="39" name="gCopySettingJSON" fieldtype="Normal" datatype="Text" comment="">
			<UUID modifications="3" userName="Jens Thorsen" accountName="jensthorsen" timestamp="2021-06-02T07:54:16">51180887-D93A-46F8-A4B4-C345A22870B4</UUID>
			<AutoEnter type="" prohibitModification="False"></AutoEnter>
			<Validation type="OnlyDuringDataEntry" allowOverride="True" notEmpty="False" unique="False" existing="False"></Validation>
			<Storage global="True" maxRepetitions="1">
				<LanguageReference name="Swedish" id="41"></LanguageReference>
			</Storage>
		</Field>
		<Field id="40" name="gCopyItemType" fieldtype="Normal" datatype="Text" comment="">
			<UUID modifications="3" userName="Jens Thorsen" accountName="jensthorsen" timestamp="2021-06-02T07:54:02">6D67CA0D-BEF8-4AD3-B19F-E7F8031D991A</UUID>
			<AutoEnter type="" prohibitModification="False"></AutoEnter>
			<Validation type="OnlyDuringDataEntry" allowOverride="True" notEmpty="False" unique="False" existing="False"></Validation>
			<Storage global="True" maxRepetitions="1">
				<LanguageReference name="Swedish" id="41"></LanguageReference>
			</Storage>
		</Field>
		<Field id="41" name="gLayoutNavigationLists" fieldtype="Normal" datatype="Text" comment="">
			<UUID modifications="3" userName="jensthorsen" accountName="JensThorsen" timestamp="2022-05-03T16:00:34">239DC51C-8CFD-432A-9D70-549DB48A2512</UUID>
			<AutoEnter type="" prohibitModification="False"></AutoEnter>
			<Validation type="OnlyDuringDataEntry" allowOverride="True" notEmpty="False" unique="False" existing="False"></Validation>
			<Storage global="True" maxRepetitions="10">
				<LanguageReference name="English" id="21"></LanguageReference>
			</Storage>
		</Field>
		<Field id="43" name="gWindowList" fieldtype="Normal" datatype="Text" comment="Window names">
			<UUID modifications="4" userName="jensthorsen" accountName="JensThorsen" timestamp="2022-05-03T16:13:18">A0FC7007-30DA-423F-9CA2-75CB35A0B405</UUID>
			<AutoEnter type="" prohibitModification="False"></AutoEnter>
			<Validation type="OnlyDuringDataEntry" allowOverride="True" notEmpty="False" unique="False" existing="False"></Validation>
			<Storage global="True" maxRepetitions="1">
				<LanguageReference name="English" id="21"></LanguageReference>
			</Storage>
		</Field>
		<Field id="44" name="gTitleId" fieldtype="Normal" datatype="Text" comment="Array of current FAT Title PrimaryKey for the open windows">
			<UUID modifications="6" userName="jensthorsen" accountName="jensthorsen" timestamp="2022-05-30T11:22:56">9E129C06-3452-4BB9-8800-D5A7FEBEA947</UUID>
			<AutoEnter type="" prohibitModification="False"></AutoEnter>
			<Validation type="OnlyDuringDataEntry" allowOverride="True" notEmpty="False" unique="False" existing="False"></Validation>
			<Storage global="True" maxRepetitions="10">
				<LanguageReference name="English" id="21"></LanguageReference>
			</Storage>
		</Field>
		<Field id="46" name="gLocalisationCode" fieldtype="Normal" datatype="Text" comment="Array of current localisation codes. If empty = Original language">
			<UUID modifications="6" userName="jensthorsen" accountName="jensthorsen" timestamp="2022-05-30T11:21:53">A7F23CB8-555A-4064-B4EA-AD68F7920A01</UUID>
			<AutoEnter type="" prohibitModification="False"></AutoEnter>
			<Validation type="OnlyDuringDataEntry" allowOverride="True" notEmpty="False" unique="False" existing="False"></Validation>
			<Storage global="True" maxRepetitions="10">
				<LanguageReference name="English" id="21"></LanguageReference>
			</Storage>
		</Field>
		<Field id="47" name="gHierarchyType" fieldtype="Normal" datatype="Text" comment="Array of active windows Hierarchy types">
			<UUID modifications="6" userName="jensthorsen" accountName="jensthorsen" timestamp="2022-05-30T11:22:38">8711F5AC-541E-4D00-B0B5-052DC46D31ED</UUID>
			<AutoEnter type="" prohibitModification="False"></AutoEnter>
			<Validation type="OnlyDuringDataEntry" allowOverride="True" notEmpty="False" unique="False" existing="False"></Validation>
			<Storage global="True" maxRepetitions="10">
				<LanguageReference name="English" id="21"></LanguageReference>
			</Storage>
		</Field>
		<Field id="48" name="gHierarchyPath" fieldtype="Normal" datatype="Text" comment="Array of active windows Hierarchy paths">
			<UUID modifications="7" userName="jensthorsen" accountName="jensthorsen" timestamp="2022-05-30T11:23:18">D494D829-85C5-4957-B2FF-385F9908A80E</UUID>
			<AutoEnter type="" prohibitModification="False"></AutoEnter>
			<Validation type="OnlyDuringDataEntry" allowOverride="True" notEmpty="False" unique="False" existing="False"></Validation>
			<Storage global="True" maxRepetitions="10">
				<LanguageReference name="English" id="21"></LanguageReference>
			</Storage>
		</Field>
		<Field id="49" name="gHierarchyLevel" fieldtype="Normal" datatype="Text" comment="Array of active windows Hierarchy levels">
			<UUID modifications="8" userName="jensthorsen" accountName="jensthorsen" timestamp="2022-05-30T11:23:35">0BF59E93-1696-4BF7-BEBF-A34CE78223A1</UUID>
			<AutoEnter type="" prohibitModification="False"></AutoEnter>
			<Validation type="OnlyDuringDataEntry" allowOverride="True" notEmpty="False" unique="False" existing="False"></Validation>
			<Storage global="True" maxRepetitions="10">
				<LanguageReference name="English" id="21"></LanguageReference>
			</Storage>
		</Field>
		<Field id="50" name="gTitleExplorerNavigation" fieldtype="Normal" datatype="Text" comment="">
			<UUID modifications="2" userName="jensthorsen" accountName="jensthorsen" timestamp="2023-05-27T12:29:20">35C7620A-34FD-45DE-9B51-D1A772DB1952</UUID>
			<AutoEnter type="" prohibitModification="False"></AutoEnter>
			<Validation type="OnlyDuringDataEntry" allowOverride="True" notEmpty="False" unique="False" existing="False"></Validation>
			<Storage global="True" maxRepetitions="1">
				<LanguageReference name="English" id="21"></LanguageReference>
			</Storage>
		</Field>
		<Field id="51" name="Title default image LMS" fieldtype="Normal" datatype="Binary" comment="">
			<UUID modifications="3" userName="jensthorsen" accountName="jensthorsen" timestamp="2023-08-13T10:40:23">55EFFCB6-39C8-4CE2-94B6-EA8C9B37E141</UUID>
			<AutoEnter type="" prohibitModification="False"></AutoEnter>
			<Validation type="OnlyDuringDataEntry" allowOverride="True" notEmpty="False" unique="False" existing="False"></Validation>
			<Storage global="False" maxRepetitions="1"></Storage>
		</Field>
		<Field id="52" name="Title default image Other" fieldtype="Normal" datatype="Binary" comment="">
			<UUID modifications="4" userName="jensthorsen" accountName="jensthorsen" timestamp="2023-08-13T10:40:29">FF3D147D-E8C2-48C6-BE7E-C29D48E1098C</UUID>
			<AutoEnter type="" prohibitModification="False"></AutoEnter>
			<Validation type="OnlyDuringDataEntry" allowOverride="True" notEmpty="False" unique="False" existing="False"></Validation>
			<Storage global="False" maxRepetitions="1"></Storage>
		</Field>
		<Field id="53" name="gHelpURLDeveloper" fieldtype="Normal" datatype="Text" comment="">
			<UUID modifications="2" userName="jensthorsen" accountName="jensthorsen" timestamp="2024-01-16T18:36:01">63FD462A-6CF3-44E2-AFAB-94FE1CDCF00C</UUID>
			<AutoEnter type="" prohibitModification="False"></AutoEnter>
			<Validation type="OnlyDuringDataEntry" allowOverride="True" notEmpty="False" unique="False" existing="False"></Validation>
			<Storage global="True" maxRepetitions="1">
				<LanguageReference name="Unicode" id="2"></LanguageReference>
			</Storage>
		</Field>
		<Field id="54" name="gHelpURLAuthor" fieldtype="Normal" datatype="Text" comment="">
			<UUID modifications="2" userName="jensthorsen" accountName="jensthorsen" timestamp="2024-01-16T18:35:37">6B98CCB6-4AD4-4143-9A4E-07BF85A96720</UUID>
			<AutoEnter type="" prohibitModification="False"></AutoEnter>
			<Validation type="OnlyDuringDataEntry" allowOverride="True" notEmpty="False" unique="False" existing="False"></Validation>
			<Storage global="True" maxRepetitions="1">
				<LanguageReference name="Unicode" id="2"></LanguageReference>
			</Storage>
		</Field>
		<Field id="55" name="gHelpURLEditor" fieldtype="Normal" datatype="Text" comment="">
			<UUID modifications="3" userName="jensthorsen" accountName="jensthorsen" timestamp="2024-01-16T18:35:44">D98D8D1A-A356-47A0-8B2E-3580E8569C94</UUID>
			<AutoEnter type="" prohibitModification="False"></AutoEnter>
			<Validation type="OnlyDuringDataEntry" allowOverride="True" notEmpty="False" unique="False" existing="False"></Validation>
			<Storage global="True" maxRepetitions="1">
				<LanguageReference name="Unicode" id="2"></LanguageReference>
			</Storage>
		</Field>
		<Field id="56" name="gHelpURLTranslator" fieldtype="Normal" datatype="Text" comment="">
			<UUID modifications="4" userName="jensthorsen" accountName="jensthorsen" timestamp="2024-01-16T18:35:53">27FEC5E2-42BE-4B04-B510-8A5D38CEEA5F</UUID>
			<AutoEnter type="" prohibitModification="False"></AutoEnter>
			<Validation type="OnlyDuringDataEntry" allowOverride="True" notEmpty="False" unique="False" existing="False"></Validation>
			<Storage global="True" maxRepetitions="1">
				<LanguageReference name="Unicode" id="2"></LanguageReference>
			</Storage>
		</Field>
		<Field id="57" name="gReviewComment" fieldtype="Normal" datatype="Text" comment="Used for displaying review comments from Funkis Cloud">
			<UUID modifications="2" userName="jensthorsen" accountName="jensthorsen" timestamp="2025-01-15T18:44:01">312279F1-792D-4966-946E-22D934624283</UUID>
			<AutoEnter type="" prohibitModification="False"></AutoEnter>
			<Validation type="OnlyDuringDataEntry" allowOverride="True" notEmpty="False" unique="False" existing="False"></Validation>
			<Storage global="True" maxRepetitions="1">
				<LanguageReference name="English" id="21"></LanguageReference>
			</Storage>
		</Field>
		<Field id="58" name="gOpen AI API Key" fieldtype="Normal" datatype="Text" comment="">
			<UUID modifications="6" userName="jensthorsen" accountName="jensthorsen" timestamp="2025-02-09T12:14:01">A692BBC1-F67D-4482-B8B9-0E021F5053E5</UUID>
			<AutoEnter type="" prohibitModification="False"></AutoEnter>
			<Validation type="OnlyDuringDataEntry" allowOverride="True" notEmpty="False" unique="False" existing="False"></Validation>
			<Storage global="True" maxRepetitions="1">
				<LanguageReference name="Unicode" id="2"></LanguageReference>
			</Storage>
		</Field>
		<Field id="59" name="gOpen AI API URL" fieldtype="Normal" datatype="Text" comment="">
			<UUID modifications="4" userName="jensthorsen" accountName="jensthorsen" timestamp="2025-02-09T12:14:12">54B47A80-1D49-48F0-B17E-431FC67E2F55</UUID>
			<AutoEnter type="" prohibitModification="False"></AutoEnter>
			<Validation type="OnlyDuringDataEntry" allowOverride="True" notEmpty="False" unique="False" existing="False"></Validation>
			<Storage global="True" maxRepetitions="1">
				<LanguageReference name="Unicode" id="2"></LanguageReference>
			</Storage>
		</Field>
		<Field id="60" name="gOpen AI API Model" fieldtype="Normal" datatype="Text" comment="">
			<UUID modifications="5" userName="jensthorsen" accountName="jensthorsen" timestamp="2025-02-09T12:14:19">2A10B872-D2F1-4AAB-BDC3-DD10B8A44645</UUID>
			<AutoEnter type="" prohibitModification="False"></AutoEnter>
			<Validation type="OnlyDuringDataEntry" allowOverride="True" notEmpty="False" unique="False" existing="False"></Validation>
			<Storage global="True" maxRepetitions="1">
				<LanguageReference name="Unicode" id="2"></LanguageReference>
			</Storage>
		</Field>
		<Field id="61" name="FAT documentation for AI Prompt" fieldtype="Normal" datatype="Text" comment="">
			<UUID modifications="2" userName="jensthorsen" accountName="jensthorsen" timestamp="2025-02-09T18:30:22">44A5A465-2D7C-47AD-B78C-7E1868092E98</UUID>
			<AutoEnter type="" prohibitModification="False"></AutoEnter>
			<Validation type="OnlyDuringDataEntry" allowOverride="True" notEmpty="False" unique="False" existing="False"></Validation>
			<Storage autoIndex="True" global="False" maxRepetitions="1">
				<LanguageReference name="English" id="21"></LanguageReference>
			</Storage>
		</Field>
		<Field id="62" name="gAIPromptFoundation" fieldtype="Normal" datatype="Text" comment="">
			<UUID modifications="2" userName="jensthorsen" accountName="jensthorsen" timestamp="2025-02-09T18:30:28">FA3715D8-F766-45EC-844D-030FDA0758EC</UUID>
			<AutoEnter type="" prohibitModification="False"></AutoEnter>
			<Validation type="OnlyDuringDataEntry" allowOverride="True" notEmpty="False" unique="False" existing="False"></Validation>
			<Storage global="True" maxRepetitions="1">
				<LanguageReference name="English" id="21"></LanguageReference>
			</Storage>
		</Field>
		<Field id="63" name="Minified MarkDown Parser" fieldtype="Normal" datatype="Text" comment="">
			<UUID modifications="2" userName="jensthorsen" accountName="jensthorsen" timestamp="2025-02-09T18:56:23">73F3930E-1A5A-4C25-BE42-4F31069D5449</UUID>
			<AutoEnter type="" prohibitModification="False"></AutoEnter>
			<Validation type="OnlyDuringDataEntry" allowOverride="True" notEmpty="False" unique="False" existing="False"></Validation>
			<Storage autoIndex="True" global="False" maxRepetitions="1">
				<LanguageReference name="Unicode" id="2"></LanguageReference>
			</Storage>
		</Field>
		<Field id="64" name="gMinifiedMarkDownParser" fieldtype="Normal" datatype="Text" comment="">
			<UUID modifications="2" userName="jensthorsen" accountName="jensthorsen" timestamp="2025-02-09T18:56:31">FCE862F5-BD16-4A34-9708-CCF801FB6DC9</UUID>
			<AutoEnter type="" prohibitModification="False"></AutoEnter>
			<Validation type="OnlyDuringDataEntry" allowOverride="True" notEmpty="False" unique="False" existing="False"></Validation>
			<Storage global="True" maxRepetitions="1">
				<LanguageReference name="Unicode" id="2"></LanguageReference>
			</Storage>
		</Field>
		<Field id="65" name="gCopyHTMLText" fieldtype="Normal" datatype="Text" comment="">
			<UUID modifications="5" userName="jensthorsen" accountName="jensthorsen" timestamp="2025-04-08T11:55:15">0B721C52-CAB7-4374-9AD0-8BCD53855B0F</UUID>
			<AutoEnter type="" prohibitModification="False"></AutoEnter>
			<Validation type="OnlyDuringDataEntry" allowOverride="True" notEmpty="False" unique="False" existing="False"></Validation>
			<Storage global="True" maxRepetitions="1">
				<LanguageReference name="Unicode" id="2"></LanguageReference>
			</Storage>
		</Field>
	</ObjectList>
</FieldCatalog>
