<ValueList>
	<ValueListReference id="158" name="Base Project FAT version"></ValueListReference>
	<Source value="FromField"></Source>
	<Field>
		<PrimaryField show="False" sort="False">
			<FieldReference id="14" name="PrimaryKey">
				<TableOccurrenceReference id="1065809" name="Baseproject FAT version CB"></TableOccurrenceReference>
			</FieldReference>
		</PrimaryField>
		<SecondaryField show="True" sort="True">
			<FieldReference id="13" name="FAT Version Name">
				<TableOccurrenceReference id="1065809" name="Baseproject FAT version CB"></TableOccurrenceReference>
			</FieldReference>
		</SecondaryField>
		<ShowRelated value="False"></ShowRelated>
	</Field>
</ValueList>
