<ValueList>
	<ValueListReference id="89" name="Page type"></ValueListReference>
	<Source value="FromField"></Source>
	<Field>
		<PrimaryField show="False" sort="False">
			<FieldReference id="1" name="PrimaryKey">
				<TableOccurrenceReference id="1065487" name="Page type template VL"></TableOccurrenceReference>
			</FieldReference>
		</PrimaryField>
		<SecondaryField show="True" sort="True">
			<FieldReference id="6" name="Page type">
				<TableOccurrenceReference id="1065487" name="Page type template VL"></TableOccurrenceReference>
			</FieldReference>
		</SecondaryField>
		<ShowRelated value="True">
			<TableOccurrenceReference id="1065126" name="FAT Package"></TableOccurrenceReference>
		</ShowRelated>
	</Field>
</ValueList>
